botprint/BotPrint.py
botprint/__init__.py
botprint-1.0.1.dist-info/LICENSE
botprint-1.0.1.dist-info/METADATA
botprint-1.0.1.dist-info/WHEEL
botprint-1.0.1.dist-info/top_level.txt
botprint-1.0.1.dist-info/RECORD
