Metadata-Version: 2.1
Name: botprint
Version: 1.0.1
Summary: A small Package for printing in Discord
Home-page: https://gitlab.com/Whitekeks/botprint.git
Author: Whitekeks
Author-email: JanNiklasb1998@gmail.com
License: UNKNOWN
Platform: UNKNOWN
Classifier: Programming Language :: Python :: 3
Classifier: License :: OSI Approved :: MIT License
Classifier: Operating System :: OS Independent
Requires-Python: >=3.7
